mcp_devtools_cli.py
server.py
mcp_devtools/__init__.py
mcp_devtools/snapshot_utils.py
mcp_devtools/snapshot_utils.pyi
mcp_devtools-2.2.14.dist-info/licenses/LICENSE
mcp_devtools-2.2.14.dist-info/METADATA
mcp_devtools-2.2.14.dist-info/WHEEL
mcp_devtools-2.2.14.dist-info/entry_points.txt
mcp_devtools-2.2.14.dist-info/top_level.txt
mcp_devtools-2.2.14.dist-info/RECORD
