Metadata-Version: 2.4
Name: mcp-devtools
Version: 2.2.14
Summary: multi-functional MCP-devtools server over SSE
Author-email: daoch4n <daoch4n@gmail.com>
License: Unlicense
Project-URL: Homepage, https://github.com/daoch4n/mcp-devtools
Project-URL: Bug Tracker, https://github.com/daoch4n/mcp-devtools/issues
Classifier: Programming Language :: Python :: 3
Classifier: Operating System :: OS Independent
Requires-Python: >=3.12
License-File: LICENSE
Requires-Dist: fastapi
Requires-Dist: uvicorn
Requires-Dist: mcp-server-git
Requires-Dist: httpx
Requires-Dist: python-dotenv
Requires-Dist: PyYAML
Dynamic: license-file
